alooyupd/__init__.py
alooyupd/check_update.py
alooyupd/version.py
alooyupd-1.0.8.dist-info/LICENCE
alooyupd-1.0.8.dist-info/METADATA
alooyupd-1.0.8.dist-info/WHEEL
alooyupd-1.0.8.dist-info/top_level.txt
alooyupd-1.0.8.dist-info/RECORD
